object_detection/__init__.py
object_detection/eval_util.py
object_detection/eval_util_test.py
object_detection/export_inference_graph.py
object_detection/export_tflite_ssd_graph.py
object_detection/export_tflite_ssd_graph_lib.py
object_detection/export_tflite_ssd_graph_lib_test.py
object_detection/exporter.py
object_detection/exporter_test.py
object_detection/inputs.py
object_detection/inputs_test.py
object_detection/model_hparams.py
object_detection/model_lib.py
object_detection/model_lib_test.py
object_detection/model_main.py
object_detection/model_tpu_main.py
object_detection/anchor_generators/__init__.py
object_detection/anchor_generators/grid_anchor_generator.py
object_detection/anchor_generators/grid_anchor_generator_test.py
object_detection/anchor_generators/multiple_grid_anchor_generator.py
object_detection/anchor_generators/multiple_grid_anchor_generator_test.py
object_detection/anchor_generators/multiscale_grid_anchor_generator.py
object_detection/anchor_generators/multiscale_grid_anchor_generator_test.py
object_detection/box_coders/__init__.py
object_detection/box_coders/faster_rcnn_box_coder.py
object_detection/box_coders/faster_rcnn_box_coder_test.py
object_detection/box_coders/keypoint_box_coder.py
object_detection/box_coders/keypoint_box_coder_test.py
object_detection/box_coders/mean_stddev_box_coder.py
object_detection/box_coders/mean_stddev_box_coder_test.py
object_detection/box_coders/square_box_coder.py
object_detection/box_coders/square_box_coder_test.py
object_detection/builders/__init__.py
object_detection/builders/anchor_generator_builder.py
object_detection/builders/anchor_generator_builder_test.py
object_detection/builders/box_coder_builder.py
object_detection/builders/box_coder_builder_test.py
object_detection/builders/box_predictor_builder.py
object_detection/builders/box_predictor_builder_test.py
object_detection/builders/dataset_builder.py
object_detection/builders/dataset_builder_test.py
object_detection-0.0.3.dist-info/LICENSE
object_detection-0.0.3.dist-info/METADATA
object_detection-0.0.3.dist-info/WHEEL
object_detection-0.0.3.dist-info/top_level.txt
object_detection-0.0.3.dist-info/RECORD
